airflow/providers/google/__init__.py
airflow/providers/google/ads/__init__.py
airflow/providers/google/ads/example_dags/__init__.py
airflow/providers/google/ads/example_dags/example_ads.py
airflow/providers/google/ads/hooks/__init__.py
airflow/providers/google/ads/hooks/ads.py
airflow/providers/google/ads/operators/__init__.py
airflow/providers/google/ads/operators/ads.py
airflow/providers/google/ads/transfers/__init__.py
airflow/providers/google/ads/transfers/ads_to_gcs.py
airflow/providers/google/cloud/__init__.py
airflow/providers/google/cloud/_internal_client/__init__.py
airflow/providers/google/cloud/_internal_client/secret_manager_client.py
airflow/providers/google/cloud/example_dags/__init__.py
airflow/providers/google/cloud/example_dags/example_automl_nl_text_classification.py
airflow/providers/google/cloud/example_dags/example_automl_nl_text_extraction.py
airflow/providers/google/cloud/example_dags/example_automl_nl_text_sentiment.py
airflow/providers/google/cloud/example_dags/example_automl_tables.py
airflow/providers/google/cloud/example_dags/example_automl_translation.py
airflow/providers/google/cloud/example_dags/example_automl_video_intelligence_classification.py
airflow/providers/google/cloud/example_dags/example_automl_video_intelligence_tracking.py
airflow/providers/google/cloud/example_dags/example_automl_vision_classification.py
airflow/providers/google/cloud/example_dags/example_automl_vision_object_detection.py
airflow/providers/google/cloud/example_dags/example_bigquery_dts.py
airflow/providers/google/cloud/example_dags/example_bigquery_operations.py
airflow/providers/google/cloud/example_dags/example_bigquery_queries.py
airflow/providers/google/cloud/example_dags/example_bigquery_to_bigquery.py
airflow/providers/google/cloud/example_dags/example_bigquery_to_gcs.py
airflow/providers/google/cloud/example_dags/example_bigquery_transfer.py
airflow/providers/google/cloud/example_dags/example_bigtable.py
apache_airflow_backport_providers_google-2020.6.24.dist-info/LICENSE
apache_airflow_backport_providers_google-2020.6.24.dist-info/LICENSE-bootstrap-toggle.txt
apache_airflow_backport_providers_google-2020.6.24.dist-info/LICENSE-bootstrap.txt
apache_airflow_backport_providers_google-2020.6.24.dist-info/LICENSE-bootstrap3-typeahead.txt
apache_airflow_backport_providers_google-2020.6.24.dist-info/LICENSE-d3-tip.txt
apache_airflow_backport_providers_google-2020.6.24.dist-info/LICENSE-d3js.txt
apache_airflow_backport_providers_google-2020.6.24.dist-info/LICENSE-dagre-d3.txt
apache_airflow_backport_providers_google-2020.6.24.dist-info/LICENSE-datatables.txt
apache_airflow_backport_providers_google-2020.6.24.dist-info/LICENSE-elasticmock.txt
apache_airflow_backport_providers_google-2020.6.24.dist-info/LICENSE-eonasdan-bootstrap-datetimepicker.txt
apache_airflow_backport_providers_google-2020.6.24.dist-info/LICENSE-flask-kerberos.txt
apache_airflow_backport_providers_google-2020.6.24.dist-info/LICENSE-hue.txt
apache_airflow_backport_providers_google-2020.6.24.dist-info/LICENSE-jqclock.txt
apache_airflow_backport_providers_google-2020.6.24.dist-info/LICENSE-jquery.txt
apache_airflow_backport_providers_google-2020.6.24.dist-info/LICENSE-moment-strftime.txt
apache_airflow_backport_providers_google-2020.6.24.dist-info/LICENSE-moment.txt
apache_airflow_backport_providers_google-2020.6.24.dist-info/LICENSE-normalize.txt
apache_airflow_backport_providers_google-2020.6.24.dist-info/LICENSE-python-nvd3.txt
apache_airflow_backport_providers_google-2020.6.24.dist-info/LICENSE-python-slugify.txt
apache_airflow_backport_providers_google-2020.6.24.dist-info/METADATA
apache_airflow_backport_providers_google-2020.6.24.dist-info/NOTICE
apache_airflow_backport_providers_google-2020.6.24.dist-info/WHEEL
apache_airflow_backport_providers_google-2020.6.24.dist-info/top_level.txt
apache_airflow_backport_providers_google-2020.6.24.dist-info/RECORD
