Metadata-Version: 2.1
Name: apache-airflow-backport-providers-google
Version: 2020.6.24
Summary: Back-ported airflow.providers.google.* package for Airflow 1.10.*
Home-page: UNKNOWN
Author: Apache Airflow PMC
Author-email: dev@airflow.apache.org
License: Apache License 2.0
Platform: UNKNOWN
Classifier: Development Status :: 5 - Production/Stable
Classifier: Environment :: Console
Classifier: Intended Audience :: Developers
Classifier: Intended Audience :: System Administrators
Classifier: License :: OSI Approved :: Apache Software License
Classifier: Programming Language :: Python :: 3.6
Classifier: Programming Language :: Python :: 3.7
Classifier: Topic :: System :: Monitoring
Requires-Python: >=3.6
Requires-Dist: apache-airflow (~=1.10)
Requires-Dist: PyOpenSSL
Requires-Dist: google-ads (>=4.0.0)
Requires-Dist: google-api-python-client (<2.0.0dev,>=1.6.0)
Requires-Dist: google-auth (<2.0.0dev,>=1.0.0)
Requires-Dist: google-auth-httplib2 (>=0.0.1)
Requires-Dist: google-cloud-automl (>=0.4.0)
Requires-Dist: google-cloud-bigquery-datatransfer (>=0.4.0)
Requires-Dist: google-cloud-bigtable (>=1.0.0)
Requires-Dist: google-cloud-container (>=0.1.1)
Requires-Dist: google-cloud-datacatalog (<0.8,>=0.5.0)
Requires-Dist: google-cloud-dataproc (>=0.5.0)
Requires-Dist: google-cloud-dlp (>=0.11.0)
Requires-Dist: google-cloud-kms (>=1.2.1)
Requires-Dist: google-cloud-language (>=1.1.1)
Requires-Dist: google-cloud-logging (>=1.14.0)
Requires-Dist: google-cloud-monitoring (>=0.34.0)
Requires-Dist: google-cloud-pubsub (>=1.0.0)
Requires-Dist: google-cloud-redis (>=0.3.0)
Requires-Dist: google-cloud-secret-manager (>=0.2.0)
Requires-Dist: google-cloud-spanner (>=1.10.0)
Requires-Dist: google-cloud-speech (>=0.36.3)
Requires-Dist: google-cloud-storage (>=1.16)
Requires-Dist: google-cloud-tasks (>=1.2.1)
Requires-Dist: google-cloud-texttospeech (<2,>=0.4.0)
Requires-Dist: google-cloud-translate (>=1.5.0)
Requires-Dist: google-cloud-videointelligence (>=1.7.0)
Requires-Dist: google-cloud-vision (>=0.35.2)
Requires-Dist: grpcio-gcp (>=0.2.2)
Requires-Dist: pandas-gbq
Provides-Extra: amazon
Requires-Dist: apache-airflow-backport-providers-amazon ; extra == 'amazon'
Provides-Extra: apache.cassandra
Requires-Dist: apache-airflow-backport-providers-apache-cassandra ; extra == 'apache.cassandra'
Provides-Extra: cncf.kubernetes
Requires-Dist: apache-airflow-backport-providers-cncf-kubernetes ; extra == 'cncf.kubernetes'
Provides-Extra: facebook
Requires-Dist: apache-airflow-backport-providers-facebook ; extra == 'facebook'
Provides-Extra: microsoft.azure
Requires-Dist: apache-airflow-backport-providers-microsoft-azure ; extra == 'microsoft.azure'
Provides-Extra: microsoft.mssql
Requires-Dist: apache-airflow-backport-providers-microsoft-mssql ; extra == 'microsoft.mssql'
Provides-Extra: mysql
Requires-Dist: apache-airflow-backport-providers-mysql ; extra == 'mysql'
Provides-Extra: postgres
Requires-Dist: apache-airflow-backport-providers-postgres ; extra == 'postgres'
Provides-Extra: presto
Requires-Dist: apache-airflow-backport-providers-presto ; extra == 'presto'
Provides-Extra: sftp
Requires-Dist: apache-airflow-backport-providers-sftp ; extra == 'sftp'
